qmake2cmake/__init__.py
qmake2cmake/condition_simplifier.py
qmake2cmake/condition_simplifier_cache.py
qmake2cmake/helper.py
qmake2cmake/pro2cmake.py
qmake2cmake/pro_conversion_rate.py
qmake2cmake/qmake_parser.py
qmake2cmake/run_pro2cmake.py
qmake2cmake/special_case_helper.py
qmake2cmake-1.0.7.dist-info/METADATA
qmake2cmake-1.0.7.dist-info/WHEEL
qmake2cmake-1.0.7.dist-info/entry_points.txt
qmake2cmake-1.0.7.dist-info/top_level.txt
qmake2cmake-1.0.7.dist-info/RECORD
