Metadata-Version: 2.4
Name: qmake2cmake
Version: 1.0.7
Summary: QMake to CMake project file converter
Home-page: https://wiki.qt.io/qmake2cmake
Author: The Qt Company
License: GPLv3
Project-URL: Bug Tracker, https://bugreports.qt.io
Project-URL: Source, https://codereview.qt-project.org/admin/repos/qt/qmake2cmake
Keywords: qmake,cmake,development
Classifier: Development Status :: 5 - Production/Stable
Classifier: Intended Audience :: Developers
Classifier: Topic :: Software Development :: Build Tools
Classifier: License :: OSI Approved :: GNU General Public License v3 (GPLv3)
Classifier: Programming Language :: Python
Classifier: Programming Language :: Python :: 3
Classifier: Programming Language :: Python :: 3.7
Classifier: Programming Language :: Python :: 3.8
Classifier: Programming Language :: Python :: 3.9
Classifier: Programming Language :: Python :: 3.10
Classifier: Programming Language :: Python :: 3 :: Only
Requires-Python: >=3.7
Requires-Dist: pyparsing
Requires-Dist: portalocker
Requires-Dist: sympy
Requires-Dist: packaging
Requires-Dist: platformdirs
Provides-Extra: dev
Requires-Dist: mypy; extra == "dev"
Requires-Dist: flake8; extra == "dev"
Requires-Dist: black; extra == "dev"
Provides-Extra: test
Requires-Dist: pytest; extra == "test"
Requires-Dist: pytest-cov; extra == "test"
